.coveragerc
.gitlab-ci.yml
.workspace
AUTHORS
ChangeLog
LICENSE.txt
README.rst
codecov.yml
requirements.txt
setup.cfg
setup.py
test-requirements.txt
docs/Makefile
docs/authors.rst
docs/changes.rst
docs/conf.py
docs/index.rst
docs/license.rst
docs/_static/.gitignore
docs/build/doctrees/authors.doctree
docs/build/doctrees/changes.doctree
docs/build/doctrees/environment.pickle
docs/build/doctrees/index.doctree
docs/build/doctrees/license.doctree
docs/build/html/.buildinfo
docs/build/html/authors.html
docs/build/html/changes.html
docs/build/html/genindex.html
docs/build/html/index.html
docs/build/html/license.html
docs/build/html/objects.inv
docs/build/html/search.html
docs/build/html/searchindex.js
docs/build/html/_sources/authors.txt
docs/build/html/_sources/changes.txt
docs/build/html/_sources/index.txt
docs/build/html/_sources/license.txt
docs/build/html/_static/ajax-loader.gif
docs/build/html/_static/alabaster.css
docs/build/html/_static/basic.css
docs/build/html/_static/comment-bright.png
docs/build/html/_static/comment-close.png
docs/build/html/_static/comment.png
docs/build/html/_static/custom.css
docs/build/html/_static/doctools.js
docs/build/html/_static/down-pressed.png
docs/build/html/_static/down.png
docs/build/html/_static/file.png
docs/build/html/_static/jquery-1.11.1.js
docs/build/html/_static/jquery.js
docs/build/html/_static/minus.png
docs/build/html/_static/plus.png
docs/build/html/_static/pygments.css
docs/build/html/_static/searchtools.js
docs/build/html/_static/underscore-1.3.1.js
docs/build/html/_static/underscore.js
docs/build/html/_static/up-pressed.png
docs/build/html/_static/up.png
docs/build/html/_static/websupport.js
docs/build/html/_static/css/badge_only.css
docs/build/html/_static/css/theme.css
docs/build/html/_static/fonts/Inconsolata-Bold.ttf
docs/build/html/_static/fonts/Inconsolata-Regular.ttf
docs/build/html/_static/fonts/Lato-Bold.ttf
docs/build/html/_static/fonts/Lato-Regular.ttf
docs/build/html/_static/fonts/RobotoSlab-Bold.ttf
pycreate.egg-info/PKG-INFO
pycreate.egg-info/SOURCES.txt
pycreate.egg-info/dependency_links.txt
pycreate.egg-info/entry_points.txt
pycreate.egg-info/not-zip-safe
pycreate.egg-info/pbr.json
pycreate.egg-info/requires.txt
pycreate.egg-info/top_level.txt
