Metadata-Version: 1.1
Name: pycreate
Version: 0.0.4
Summary: Create ready to go python projects with a single command
Home-page: http://pythonhosted.org/pycreate
Author: Steven Cooney
Author-email: dev.sjc@gmail.com
License: MIT
Platform: UNKNOWN
Classifier: Development Status :: 3 - Alpha
Classifier: Intended Audience :: Developers
Classifier: Topic :: Software Development :: Build Tools
Classifier: Programming Language :: Python :: 3.3
Classifier: Programming Language :: Python :: 3.4
Classifier: Programming Language :: Python :: 3.5
Classifier: Programming Language :: Python :: 3.6
Classifier: Operating System :: POSIX
Classifier: Operating System :: MacOS :: MacOS X
